{
  "name": "Grove Weather",
  "showOnLockScreen": true,
  "views": [
    {
      "type": "text",
      "body": "Sat 07/26 4:45AM CT\n\u2753 Watches: None\nMesoscale Active: No\n\nRain Chance: Saturday 07/26 at 04AM (65%)\nSPC Day 1 Risk: Non-Severe T-Storms (Level 2)\nSPC Day 2 Risk: None (Level None)"
    }
  ],
  "families": [
    {
      "family": "graphicCircular",
      "class": "CLKComplicationTemplateGraphicCircularStackText",
      "line1": "\ud83d\udfe2 \ud83d\udd35",
      "line2": "\u26aa \u26aa"
    }
  ]
}