{
  "name": "Grove Weather",
  "showOnLockScreen": true,
  "views": [
    {
      "type": "text",
      "body": "Mon 11/24 10:32PM CT\nWatches: None\nMesoscale Active: No\n\nRain Chance: Friday 11/28 at 06PM (56%)\nSPC Day 1 Risk: Non-Severe T-Storms (Level 2)\nSPC Day 2 Risk: None (Level None)\n"
    }
  ],
  "families": [
    {
      "family": "graphicCircular",
      "class": "CLKComplicationTemplateGraphicCircularStackText",
      "line1": "\ud83d\udfe9 \u26ab",
      "line2": "\u26ab \u26ab"
    }
  ]
}